{
  "annotations": {
    "list": [
      {
        "builtIn": 1,
        "datasource": {
          "type": "datasource",
          "uid": "grafana"
        },
        "enable": true,
        "hide": true,
        "iconColor": "rgba(0, 211, 255, 1)",
        "name": "Annotations & Alerts",
        "type": "dashboard"
      }
    ]
  },
  "description": "Suitable for monitoring NVIDIA GPU resource overviews in AI intelligent computing scenarios. Dependent components: dcgm-exporter:3.3.0-3.2.0-ubuntu22.04, prometheus:v2.39.1, grafana:10.3.3",
  "editable": true,
  "fiscalYearStartMonth": 0,
  "graphTooltip": 0,
  "links": [],
  "panels": [
    {
      "collapsed": false,
      "gridPos": {
        "h": 1,
        "w": 24,
        "x": 0,
        "y": 0
      },
      "id": 50,
      "panels": [],
      "title": "GPU Resource Monitoring Overview",
      "type": "row"
    },
    {
      "datasource": {
        "type": "prometheus",
        "uid": "${idc}"
      },
      "fieldConfig": {
        "defaults": {
          "color": {
            "mode": "thresholds"
          },
          "decimals": 0,
          "mappings": [],
          "thresholds": {
            "mode": "absolute",
            "steps": [
              {
                "color": "blue",
                "value": 0
              }
            ]
          }
        },
        "overrides": [
          {
            "matcher": {
              "id": "byName",
              "options": "Unused GPU Cards"
            },
            "properties": [
              {
                "id": "color",
                "value": {
                  "fixedColor": "light-red",
                  "mode": "fixed"
                }
              }
            ]
          },
          {
            "matcher": {
              "id": "byName",
              "options": "Used GPU Cards"
            },
            "properties": [
              {
                "id": "color",
                "value": {
                  "fixedColor": "yellow",
                  "mode": "fixed"
                }
              }
            ]
          },
          {
            "matcher": {
              "id": "byName",
              "options": "Total Acceleration Chips (Cards)"
            },
            "properties": [
              {
                "id": "color",
                "value": {
                  "fixedColor": "purple",
                  "mode": "fixed"
                }
              }
            ]
          }
        ]
      },
      "gridPos": {
        "h": 7,
        "w": 8,
        "x": 0,
        "y": 1
      },
      "id": 74,
      "options": {
        "colorMode": "background",
        "graphMode": "none",
        "justifyMode": "auto",
        "orientation": "auto",
        "percentChangeColorMode": "standard",
        "reduceOptions": {
          "calcs": [
            "lastNotNull"
          ],
          "fields": "",
          "values": false
        },
        "showPercentChange": false,
        "textMode": "auto",
        "wideLayout": true
      },
      "pluginVersion": "12.4.3",
      "targets": [
        {
          "datasource": {
            "type": "prometheus",
            "uid": "${idc}"
          },
          "editorMode": "code",
          "expr": "count(DCGM_FI_DEV_GPU_UTIL{Hostname=~\"$hostname\"})/2",
          "format": "time_series",
          "instant": false,
          "legendFormat": "Total GPU Cards",
          "range": true,
          "refId": "E"
        },
        {
          "datasource": {
            "type": "prometheus",
            "uid": "${idc}"
          },
          "editorMode": "code",
          "expr": "count(DCGM_FI_DEV_GPU_UTIL{exported_pod!=\"\",Hostname=~\"$hostname\"})/2",
          "instant": false,
          "legendFormat": "Allocated GPU Cards",
          "range": true,
          "refId": "A"
        },
        {
          "datasource": {
            "type": "prometheus",
            "uid": "${idc}"
          },
          "editorMode": "code",
          "expr": "count(avg_over_time(DCGM_FI_DEV_GPU_UTIL{Hostname=~\"$hostname\"}[1m])>0)/2",
          "instant": false,
          "legendFormat": "Used GPU Cards",
          "range": true,
          "refId": "B"
        },
        {
          "datasource": {
            "type": "prometheus",
            "uid": "${idc}"
          },
          "editorMode": "code",
          "expr": "count(DCGM_FI_DEV_GPU_UTIL{exported_pod!=\"\",Hostname=~\"$hostname\"})/2-count(avg_over_time(DCGM_FI_DEV_GPU_UTIL{Hostname=~\"$hostname\"}[1m])>0)/2",
          "instant": false,
          "legendFormat": "Unused GPU Cards",
          "range": true,
          "refId": "F"
        }
      ],
      "title": "GPU Card Usage Status",
      "type": "stat"
    },
    {
      "datasource": {
        "type": "prometheus",
        "uid": "${idc}"
      },
      "fieldConfig": {
        "defaults": {
          "color": {
            "mode": "palette-classic"
          },
          "custom": {
            "axisBorderShow": false,
            "axisCenteredZero": false,
            "axisColorMode": "text",
            "axisLabel": "",
            "axisPlacement": "auto",
            "barAlignment": 0,
            "barWidthFactor": 0.6,
            "drawStyle": "line",
            "fillOpacity": 39,
            "gradientMode": "opacity",
            "hideFrom": {
              "legend": false,
              "tooltip": false,
              "viz": false
            },
            "insertNulls": false,
            "lineInterpolation": "smooth",
            "lineStyle": {
              "fill": "solid"
            },
            "lineWidth": 1,
            "pointSize": 4,
            "scaleDistribution": {
              "type": "linear"
            },
            "showPoints": "auto",
            "showValues": false,
            "spanNulls": false,
            "stacking": {
              "group": "A",
              "mode": "none"
            },
            "thresholdsStyle": {
              "mode": "off"
            }
          },
          "mappings": [],
          "min": 0,
          "thresholds": {
            "mode": "absolute",
            "steps": [
              {
                "color": "green",
                "value": 0
              },
              {
                "color": "red",
                "value": 80
              }
            ]
          }
        },
        "overrides": [
          {
            "matcher": {
              "id": "byName",
              "options": "total"
            },
            "properties": [
              {
                "id": "color",
                "value": {
                  "fixedColor": "purple",
                  "mode": "fixed"
                }
              }
            ]
          },
          {
            "matcher": {
              "id": "byName",
              "options": "request"
            },
            "properties": [
              {
                "id": "color",
                "value": {
                  "fixedColor": "orange",
                  "mode": "fixed"
                }
              },
              {
                "id": "custom.lineStyle",
                "value": {
                  "dash": [
                    20,
                    10
                  ],
                  "fill": "dash"
                }
              },
              {
                "id": "custom.lineWidth",
                "value": 2
              }
            ]
          },
          {
            "matcher": {
              "id": "byName",
              "options": "used"
            },
            "properties": [
              {
                "id": "color",
                "value": {
                  "fixedColor": "green",
                  "mode": "fixed"
                }
              }
            ]
          }
        ]
      },
      "gridPos": {
        "h": 7,
        "w": 8,
        "x": 8,
        "y": 1
      },
      "id": 84,
      "options": {
        "legend": {
          "calcs": [
            "lastNotNull",
            "max"
          ],
          "displayMode": "table",
          "placement": "bottom",
          "showLegend": true
        },
        "tooltip": {
          "hideZeros": false,
          "mode": "single",
          "sort": "none"
        }
      },
      "pluginVersion": "12.4.3",
      "targets": [
        {
          "datasource": {
            "type": "prometheus",
            "uid": "${idc}"
          },
          "editorMode": "code",
          "expr": "count(DCGM_FI_DEV_GPU_UTIL{modelName=\"NVIDIA RTX 4000 Ada Generation\",Hostname=~\"$hostname\"})/2",
          "instant": false,
          "legendFormat": "total",
          "range": true,
          "refId": "C"
        },
        {
          "datasource": {
            "type": "prometheus",
            "uid": "${idc}"
          },
          "editorMode": "code",
          "expr": "count(DCGM_FI_DEV_GPU_UTIL{exported_pod!=\"\",modelName=\"NVIDIA RTX 4000 Ada Generation\",Hostname=~\"$hostname\"})/2",
          "instant": false,
          "legendFormat": "request",
          "range": true,
          "refId": "B"
        },
        {
          "datasource": {
            "type": "prometheus",
            "uid": "${idc}"
          },
          "editorMode": "code",
          "expr": "count(DCGM_FI_DEV_GPU_UTIL{pod!=\"\",modelName=\"NVIDIA RTX 4000 Ada Generation\",Hostname=~\"$hostname\"} > 0)",
          "instant": false,
          "legendFormat": "used",
          "range": true,
          "refId": "A"
        }
      ],
      "title": "NVIDIA RTX 4000 Ada Generation",
      "type": "timeseries"
    },
    {
      "datasource": {
        "type": "prometheus",
        "uid": "${idc}"
      },
      "fieldConfig": {
        "defaults": {
          "color": {
            "mode": "palette-classic"
          },
          "custom": {
            "axisBorderShow": false,
            "axisCenteredZero": false,
            "axisColorMode": "text",
            "axisLabel": "",
            "axisPlacement": "auto",
            "barAlignment": 0,
            "barWidthFactor": 0.6,
            "drawStyle": "line",
            "fillOpacity": 39,
            "gradientMode": "opacity",
            "hideFrom": {
              "legend": false,
              "tooltip": false,
              "viz": false
            },
            "insertNulls": false,
            "lineInterpolation": "smooth",
            "lineWidth": 1,
            "pointSize": 5,
            "scaleDistribution": {
              "type": "linear"
            },
            "showPoints": "auto",
            "showValues": false,
            "spanNulls": false,
            "stacking": {
              "group": "A",
              "mode": "none"
            },
            "thresholdsStyle": {
              "mode": "off"
            }
          },
          "mappings": [],
          "min": 0,
          "thresholds": {
            "mode": "absolute",
            "steps": [
              {
                "color": "green",
                "value": 0
              },
              {
                "color": "red",
                "value": 80
              }
            ]
          }
        },
        "overrides": [
          {
            "matcher": {
              "id": "byName",
              "options": "total"
            },
            "properties": [
              {
                "id": "color",
                "value": {
                  "fixedColor": "red",
                  "mode": "fixed"
                }
              }
            ]
          },
          {
            "matcher": {
              "id": "byName",
              "options": "request"
            },
            "properties": [
              {
                "id": "color",
                "value": {
                  "fixedColor": "yellow",
                  "mode": "fixed"
                }
              },
              {
                "id": "custom.lineStyle",
                "value": {
                  "dash": [
                    20,
                    10
                  ],
                  "fill": "dash"
                }
              },
              {
                "id": "custom.lineWidth",
                "value": 2
              }
            ]
          },
          {
            "matcher": {
              "id": "byName",
              "options": "used"
            },
            "properties": [
              {
                "id": "color",
                "value": {
                  "fixedColor": "green",
                  "mode": "fixed"
                }
              }
            ]
          }
        ]
      },
      "gridPos": {
        "h": 7,
        "w": 8,
        "x": 16,
        "y": 1
      },
      "id": 83,
      "options": {
        "legend": {
          "calcs": [
            "lastNotNull",
            "max"
          ],
          "displayMode": "table",
          "placement": "bottom",
          "showLegend": true
        },
        "tooltip": {
          "hideZeros": false,
          "mode": "single",
          "sort": "none"
        }
      },
      "pluginVersion": "12.4.3",
      "targets": [
        {
          "datasource": {
            "type": "prometheus",
            "uid": "${idc}"
          },
          "editorMode": "code",
          "expr": "count(DCGM_FI_DEV_GPU_UTIL{modelName=\"NVIDIA GeForce GTX 1650\",Hostname=~\"$hostname\"})/2",
          "instant": false,
          "legendFormat": "total",
          "range": true,
          "refId": "C"
        },
        {
          "datasource": {
            "type": "prometheus",
            "uid": "${idc}"
          },
          "editorMode": "code",
          "expr": "count(DCGM_FI_DEV_GPU_UTIL{exported_pod!=\"\",modelName=\"NVIDIA GeForce GTX 1650\",Hostname=~\"$hostname\"})/2",
          "instant": false,
          "legendFormat": "request",
          "range": true,
          "refId": "B"
        },
        {
          "datasource": {
            "type": "prometheus",
            "uid": "${idc}"
          },
          "editorMode": "code",
          "expr": "count(DCGM_FI_DEV_GPU_UTIL{pod!=\"\",modelName=\"NVIDIA GeForce GTX 1650\",Hostname=~\"$hostname\"} > 0)",
          "instant": false,
          "legendFormat": "used",
          "range": true,
          "refId": "A"
        }
      ],
      "title": "NVIDIA GeForce GTX 1650",
      "type": "timeseries"
    },
    {
      "datasource": {
        "type": "prometheus",
        "uid": "prometheus"
      },
      "fieldConfig": {
        "defaults": {
          "color": {
            "mode": "thresholds"
          },
          "mappings": [],
          "max": 100,
          "min": 0,
          "thresholds": {
            "mode": "absolute",
            "steps": [
              {
                "color": "green",
                "value": 0
              },
              {
                "color": "#EAB839",
                "value": 80
              },
              {
                "color": "red",
                "value": 90
              }
            ]
          },
          "unit": "percent"
        },
        "overrides": []
      },
      "gridPos": {
        "h": 5,
        "w": 6,
        "x": 0,
        "y": 8
      },
      "id": 70,
      "options": {
        "minVizHeight": 75,
        "minVizWidth": 75,
        "orientation": "auto",
        "reduceOptions": {
          "calcs": [
            "lastNotNull"
          ],
          "fields": "",
          "values": false
        },
        "showThresholdLabels": false,
        "showThresholdMarkers": true,
        "sizing": "auto"
      },
      "pluginVersion": "12.4.3",
      "targets": [
        {
          "datasource": {
            "type": "prometheus",
            "uid": "prometheus"
          },
          "editorMode": "code",
          "expr": "count(avg_over_time(DCGM_FI_DEV_GPU_UTIL{Hostname=~\"$hostname\"}[3m])>0) \n/ \ncount(DCGM_FI_DEV_GPU_UTIL{Hostname=~\"$hostname\"}) \n* avg(DCGM_FI_DEV_GPU_UTIL{Hostname=~\"$hostname\"} > 0)",
          "instant": false,
          "legendFormat": "__auto",
          "range": true,
          "refId": "A"
        }
      ],
      "title": "Total GPU Utilization",
      "type": "gauge"
    },
    {
      "datasource": {
        "type": "prometheus",
        "uid": "prometheus"
      },
      "fieldConfig": {
        "defaults": {
          "color": {
            "mode": "thresholds"
          },
          "mappings": [],
          "max": 100,
          "min": 0,
          "thresholds": {
            "mode": "absolute",
            "steps": [
              {
                "color": "green",
                "value": 0
              },
              {
                "color": "#EAB839",
                "value": 70
              },
              {
                "color": "red",
                "value": 80
              }
            ]
          },
          "unit": "percent"
        },
        "overrides": []
      },
      "gridPos": {
        "h": 5,
        "w": 6,
        "x": 6,
        "y": 8
      },
      "id": 68,
      "options": {
        "minVizHeight": 75,
        "minVizWidth": 75,
        "orientation": "auto",
        "reduceOptions": {
          "calcs": [
            "lastNotNull"
          ],
          "fields": "",
          "values": false
        },
        "showThresholdLabels": false,
        "showThresholdMarkers": true,
        "sizing": "auto"
      },
      "pluginVersion": "12.4.3",
      "targets": [
        {
          "datasource": {
            "type": "prometheus",
            "uid": "prometheus"
          },
          "editorMode": "code",
          "expr": "avg(DCGM_FI_DEV_GPU_UTIL{Hostname=~\"$hostname\"} > 0)",
          "instant": false,
          "legendFormat": "__auto",
          "queryType": "randomWalk",
          "range": true,
          "refId": "A"
        }
      ],
      "title": "Utilized GPU Utilization",
      "type": "gauge"
    },
    {
      "datasource": {
        "type": "prometheus",
        "uid": "${idc}"
      },
      "fieldConfig": {
        "defaults": {
          "color": {
            "mode": "thresholds"
          },
          "mappings": [],
          "max": 88000,
          "min": 0,
          "thresholds": {
            "mode": "absolute",
            "steps": [
              {
                "color": "green",
                "value": 0
              },
              {
                "color": "#EAB839",
                "value": 44000
              },
              {
                "color": "red",
                "value": 70400
              }
            ]
          },
          "unit": "watt"
        },
        "overrides": []
      },
      "gridPos": {
        "h": 5,
        "w": 6,
        "x": 12,
        "y": 8
      },
      "id": 75,
      "options": {
        "minVizHeight": 75,
        "minVizWidth": 75,
        "orientation": "auto",
        "reduceOptions": {
          "calcs": [
            "lastNotNull"
          ],
          "fields": "",
          "values": false
        },
        "showThresholdLabels": false,
        "showThresholdMarkers": true,
        "sizing": "auto"
      },
      "pluginVersion": "12.4.3",
      "targets": [
        {
          "datasource": {
            "type": "prometheus",
            "uid": "P1809F7CD0C75ACF3"
          },
          "editorMode": "code",
          "expr": "sum(DCGM_FI_DEV_POWER_USAGE{Hostname=~\"$hostname\"})",
          "instant": false,
          "legendFormat": "__auto",
          "range": true,
          "refId": "A"
        }
      ],
      "title": "Total GPU Power Consumption",
      "type": "gauge"
    },
    {
      "datasource": {
        "type": "prometheus",
        "uid": "${idc}"
      },
      "fieldConfig": {
        "defaults": {
          "color": {
            "mode": "thresholds"
          },
          "mappings": [],
          "max": 90,
          "min": 0,
          "thresholds": {
            "mode": "absolute",
            "steps": [
              {
                "color": "green",
                "value": 0
              },
              {
                "color": "#EAB839",
                "value": 60
              },
              {
                "color": "red",
                "value": 80
              }
            ]
          },
          "unit": "celsius"
        },
        "overrides": []
      },
      "gridPos": {
        "h": 5,
        "w": 6,
        "x": 18,
        "y": 8
      },
      "id": 82,
      "options": {
        "minVizHeight": 75,
        "minVizWidth": 75,
        "orientation": "horizontal",
        "reduceOptions": {
          "calcs": [
            "lastNotNull"
          ],
          "fields": "",
          "values": false
        },
        "showThresholdLabels": false,
        "showThresholdMarkers": true,
        "sizing": "auto"
      },
      "pluginVersion": "12.4.3",
      "targets": [
        {
          "datasource": {
            "type": "prometheus",
            "uid": "P1809F7CD0C75ACF3"
          },
          "editorMode": "code",
          "expr": "avg(DCGM_FI_DEV_GPU_TEMP{Hostname=~\"$hostname\"})",
          "instant": false,
          "legendFormat": "__auto",
          "range": true,
          "refId": "A"
        }
      ],
      "title": "GPU Average Temperature",
      "type": "gauge"
    },
    {
      "datasource": {
        "type": "prometheus",
        "uid": "prometheus"
      },
      "description": "Monitoring and displaying NVIDIA driver versions, chip types, GPU card health status, etc.",
      "fieldConfig": {
        "defaults": {
          "color": {
            "mode": "thresholds"
          },
          "custom": {
            "align": "center",
            "cellOptions": {
              "type": "auto"
            },
            "footer": {
              "reducers": []
            },
            "inspect": false
          },
          "mappings": [],
          "thresholds": {
            "mode": "absolute",
            "steps": [
              {
                "color": "green",
                "value": 0
              },
              {
                "color": "red",
                "value": 80
              }
            ]
          }
        },
        "overrides": [
          {
            "matcher": {
              "id": "byName",
              "options": "GPU Card Status"
            },
            "properties": [
              {
                "id": "custom.cellOptions",
                "value": {
                  "type": "color-background"
                }
              },
              {
                "id": "mappings",
                "value": [
                  {
                    "options": {
                      "from": 0,
                      "result": {
                        "color": "green",
                        "index": 0,
                        "text": "OK"
                      },
                      "to": 8
                    },
                    "type": "range"
                  },
                  {
                    "options": {
                      "match": "null+nan",
                      "result": {
                        "color": "red",
                        "index": 1,
                        "text": "Error"
                      }
                    },
                    "type": "special"
                  }
                ]
              },
              {
                "id": "custom.width",
                "value": 174
              }
            ]
          },
          {
            "matcher": {
              "id": "byName",
              "options": "Chip Type"
            },
            "properties": [
              {
                "id": "custom.cellOptions",
                "value": {
                  "type": "color-background"
                }
              },
              {
                "id": "color",
                "value": {
                  "fixedColor": "blue",
                  "mode": "fixed"
                }
              },
              {
                "id": "custom.width",
                "value": 253
              }
            ]
          },
          {
            "matcher": {
              "id": "byName",
              "options": "Hostname"
            },
            "properties": [
              {
                "id": "custom.cellOptions",
                "value": {
                  "type": "color-text"
                }
              },
              {
                "id": "color",
                "value": {
                  "fixedColor": "blue",
                  "mode": "fixed"
                }
              },
              {
                "id": "custom.width",
                "value": 151
              }
            ]
          },
          {
            "matcher": {
              "id": "byName",
              "options": "Host IP"
            },
            "properties": [
              {
                "id": "custom.cellOptions",
                "value": {
                  "type": "color-text"
                }
              },
              {
                "id": "color",
                "value": {
                  "fixedColor": "blue",
                  "mode": "fixed"
                }
              },
              {
                "id": "custom.width",
                "value": 126
              }
            ]
          },
          {
            "matcher": {
              "id": "byName",
              "options": "NVIDIA Driver Version"
            },
            "properties": [
              {
                "id": "custom.cellOptions",
                "value": {
                  "type": "color-text"
                }
              },
              {
                "id": "color",
                "value": {
                  "fixedColor": "orange",
                  "mode": "fixed"
                }
              },
              {
                "id": "custom.width",
                "value": 171
              }
            ]
          },
          {
            "matcher": {
              "id": "byName",
              "options": "Memory Clock Frequency"
            },
            "properties": [
              {
                "id": "unit",
                "value": "rothz"
              },
              {
                "id": "custom.cellOptions",
                "value": {
                  "type": "color-text"
                }
              },
              {
                "id": "color",
                "value": {
                  "fixedColor": "yellow",
                  "mode": "shades"
                }
              },
              {
                "id": "custom.width",
                "value": 209
              }
            ]
          },
          {
            "matcher": {
              "id": "byName",
              "options": "SM Clock Frequency"
            },
            "properties": [
              {
                "id": "unit",
                "value": "rothz"
              },
              {
                "id": "custom.cellOptions",
                "value": {
                  "type": "color-text"
                }
              },
              {
                "id": "color",
                "value": {
                  "fixedColor": "yellow",
                  "mode": "fixed"
                }
              },
              {
                "id": "custom.width",
                "value": 213
              }
            ]
          },
          {
            "matcher": {
              "id": "byName",
              "options": "GPU Total Memory"
            },
            "properties": [
              {
                "id": "unit",
                "value": "mbytes"
              },
              {
                "id": "custom.width",
                "value": 170
              }
            ]
          },
          {
            "matcher": {
              "id": "byName",
              "options": "GPU Memory Usage"
            },
            "properties": [
              {
                "id": "unit",
                "value": "percentunit"
              },
              {
                "id": "custom.cellOptions",
                "value": {
                  "mode": "lcd",
                  "type": "gauge"
                }
              },
              {
                "id": "min",
                "value": 0
              },
              {
                "id": "max",
                "value": 1
              }
            ]
          },
          {
            "matcher": {
              "id": "byName",
              "options": "GPU Temperature"
            },
            "properties": [
              {
                "id": "unit",
                "value": "celsius"
              },
              {
                "id": "custom.cellOptions",
                "value": {
                  "mode": "lcd",
                  "type": "gauge",
                  "valueDisplayMode": "text"
                }
              },
              {
                "id": "min",
                "value": 0
              },
              {
                "id": "max",
                "value": 100
              }
            ]
          }
        ]
      },
      "gridPos": {
        "h": 7,
        "w": 24,
        "x": 0,
        "y": 13
      },
      "id": 81,
      "options": {
        "cellHeight": "sm",
        "showHeader": true,
        "sortBy": [
          {
            "desc": true,
            "displayName": "GPU Card Status"
          }
        ]
      },
      "pluginVersion": "12.4.3",
      "targets": [
        {
          "datasource": {
            "type": "prometheus",
            "uid": "prometheus"
          },
          "editorMode": "code",
          "exemplar": false,
          "expr": "count(DCGM_FI_DEV_GPU_UTIL{Hostname=~\"$hostname\"}) by (Hostname)",
          "format": "table",
          "instant": true,
          "legendFormat": "__auto",
          "range": false,
          "refId": "A"
        },
        {
          "datasource": {
            "type": "prometheus",
            "uid": "prometheus"
          },
          "editorMode": "code",
          "exemplar": false,
          "expr": "avg by (Hostname,modelName,host_ip,DCGM_FI_DRIVER_VERSION) (DCGM_FI_DEV_GPU_UTIL{Hostname=~\"$hostname\"} * on (pod) group_left (host_ip) kube_pod_info)",
          "format": "table",
          "instant": true,
          "legendFormat": "__auto",
          "range": false,
          "refId": "B"
        },
        {
          "datasource": {
            "type": "prometheus",
            "uid": "prometheus"
          },
          "editorMode": "code",
          "exemplar": false,
          "expr": "label_replace(kube_node_info{node=~\"$hostname\"},\"Hostname\",\"$1\",\"node\",\"(.*)\")",
          "format": "table",
          "instant": true,
          "legendFormat": "__auto",
          "range": false,
          "refId": "C"
        },
        {
          "datasource": {
            "type": "prometheus",
            "uid": "prometheus"
          },
          "editorMode": "code",
          "exemplar": false,
          "expr": "(avg by (Hostname,host_ip,uuid) (DCGM_FI_DEV_FB_USED{Hostname=~\"$hostname\"}) + avg by (Hostname,host_ip,uuid) (DCGM_FI_DEV_FB_FREE{Hostname=~\"$hostname\"}))",
          "format": "table",
          "instant": true,
          "legendFormat": "CPU Utilization",
          "range": false,
          "refId": "D"
        },
        {
          "datasource": {
            "type": "prometheus",
            "uid": "prometheus"
          },
          "editorMode": "code",
          "exemplar": false,
          "expr": "avg by (Hostname,host_ip,uuid) (DCGM_FI_DEV_FB_USED{Hostname=~\"$hostname\"}) / (avg by (Hostname,host_ip,uuid) (DCGM_FI_DEV_FB_USED{Hostname=~\"$hostname\"}) + avg by (Hostname,host_ip,uuid) (DCGM_FI_DEV_FB_FREE{Hostname=~\"$hostname\"}))",
          "format": "table",
          "instant": true,
          "legendFormat": "Memory Usage",
          "range": false,
          "refId": "E"
        },
        {
          "datasource": {
            "type": "prometheus",
            "uid": "prometheus"
          },
          "editorMode": "code",
          "exemplar": false,
          "expr": "avg by (Hostname) (DCGM_FI_DEV_MEM_CLOCK{Hostname=~\"$hostname\"}*1000000)",
          "format": "table",
          "instant": true,
          "legendFormat": "Memory Clock Frequency",
          "range": false,
          "refId": "F"
        },
        {
          "datasource": {
            "type": "prometheus",
            "uid": "prometheus"
          },
          "editorMode": "code",
          "exemplar": false,
          "expr": "avg by (Hostname) (DCGM_FI_DEV_SM_CLOCK{Hostname=~\"$hostname\"}*1000000)",
          "format": "table",
          "instant": true,
          "legendFormat": "SM Clock Frequency",
          "range": false,
          "refId": "G"
        },
        {
          "datasource": {
            "type": "prometheus",
            "uid": "prometheus"
          },
          "editorMode": "code",
          "exemplar": false,
          "expr": "avg by (Hostname,host_ip,uuid) (DCGM_FI_DEV_GPU_TEMP{Hostname=~\"$hostname\"})",
          "format": "table",
          "instant": true,
          "legendFormat": "__auto",
          "range": false,
          "refId": "H"
        }
      ],
      "title": "GPU Compute Card Health Status & Version Information Overview",
      "transformations": [
        {
          "id": "merge",
          "options": {}
        },
        {
          "id": "filterFieldsByName",
          "options": {
            "include": {
              "names": [
                "Hostname",
                "Value #A",
                "DCGM_FI_DRIVER_VERSION",
                "host_ip",
                "modelName",
                "Value #D",
                "Value #E",
                "Value #F",
                "Value #G",
                "Value #H"
              ]
            }
          }
        },
        {
          "id": "organize",
          "options": {
            "excludeByName": {},
            "includeByName": {},
            "indexByName": {
              "DCGM_FI_DRIVER_VERSION": 2,
              "Hostname": 0,
              "Value #A": 4,
              "Value #D": 9,
              "Value #E": 10,
              "Value #F": 5,
              "Value #G": 6,
              "host_ip": 1,
              "kernel_version": 7,
              "modelName": 3,
              "os_image": 8
            },
            "renameByName": {
              "DCGM_FI_DRIVER_VERSION": "NVIDIA Driver Version",
              "Hostname": "Hostname",
              "Value #A": "GPU Card Status",
              "Value #D": "GPU Total Memory",
              "Value #E": "GPU Memory Usage",
              "Value #F": "Memory Clock Frequency",
              "Value #G": "SM Clock Frequency",
              "Value #H": "GPU Temperature",
              "host_ip": "Host IP",
              "kernel_version": "Kernel",
              "modelName": "Chip Type",
              "os_image": "Operating System Version",
              "release": "Kernel"
            }
          }
        }
      ],
      "type": "table"
    },
    {
      "datasource": {
        "type": "prometheus",
        "uid": "prometheus"
      },
      "description": "Monitoring and displaying host kernel and OS versions, CPU and memory utilisation, and temperature",
      "fieldConfig": {
        "defaults": {
          "color": {
            "mode": "thresholds"
          },
          "custom": {
            "align": "center",
            "cellOptions": {
              "type": "auto"
            },
            "footer": {
              "reducers": []
            },
            "inspect": false
          },
          "mappings": [],
          "thresholds": {
            "mode": "absolute",
            "steps": [
              {
                "color": "green",
                "value": 0
              },
              {
                "color": "red",
                "value": 80
              }
            ]
          }
        },
        "overrides": [
          {
            "matcher": {
              "id": "byName",
              "options": "Hostname"
            },
            "properties": [
              {
                "id": "custom.cellOptions",
                "value": {
                  "type": "color-text"
                }
              },
              {
                "id": "color",
                "value": {
                  "fixedColor": "blue",
                  "mode": "fixed"
                }
              },
              {
                "id": "custom.width",
                "value": 145
              }
            ]
          },
          {
            "matcher": {
              "id": "byName",
              "options": "Host IP"
            },
            "properties": [
              {
                "id": "custom.cellOptions",
                "value": {
                  "type": "color-text"
                }
              },
              {
                "id": "color",
                "value": {
                  "fixedColor": "blue",
                  "mode": "fixed"
                }
              },
              {
                "id": "custom.width",
                "value": 126
              }
            ]
          },
          {
            "matcher": {
              "id": "byName",
              "options": "Kernel"
            },
            "properties": [
              {
                "id": "color",
                "value": {
                  "fixedColor": "purple",
                  "mode": "fixed"
                }
              },
              {
                "id": "custom.cellOptions",
                "value": {
                  "type": "color-text"
                }
              },
              {
                "id": "custom.width",
                "value": 179
              }
            ]
          },
          {
            "matcher": {
              "id": "byName",
              "options": "Operating System Version"
            },
            "properties": [
              {
                "id": "custom.cellOptions",
                "value": {
                  "type": "color-text"
                }
              },
              {
                "id": "color",
                "value": {
                  "fixedColor": "purple",
                  "mode": "fixed"
                }
              },
              {
                "id": "custom.width",
                "value": 231
              }
            ]
          },
          {
            "matcher": {
              "id": "byName",
              "options": "CPU Utilization"
            },
            "properties": [
              {
                "id": "unit",
                "value": "percentunit"
              },
              {
                "id": "custom.cellOptions",
                "value": {
                  "mode": "lcd",
                  "type": "gauge"
                }
              },
              {
                "id": "color",
                "value": {
                  "mode": "continuous-GrYlRd"
                }
              },
              {
                "id": "min",
                "value": 0
              },
              {
                "id": "max",
                "value": 100
              },
              {
                "id": "custom.width",
                "value": 385
              }
            ]
          },
          {
            "matcher": {
              "id": "byName",
              "options": "Memory Usage"
            },
            "properties": [
              {
                "id": "custom.cellOptions",
                "value": {
                  "mode": "lcd",
                  "type": "gauge"
                }
              },
              {
                "id": "color",
                "value": {
                  "mode": "continuous-GrYlRd"
                }
              },
              {
                "id": "unit",
                "value": "percentunit"
              },
              {
                "id": "min",
                "value": 0
              },
              {
                "id": "max",
                "value": 1
              },
              {
                "id": "custom.width",
                "value": 386
              }
            ]
          },
          {
            "matcher": {
              "id": "byName",
              "options": "Host Temperature"
            },
            "properties": [
              {
                "id": "custom.cellOptions",
                "value": {
                  "mode": "lcd",
                  "type": "gauge",
                  "valueDisplayMode": "text"
                }
              },
              {
                "id": "unit",
                "value": "celsius"
              },
              {
                "id": "min",
                "value": 0
              },
              {
                "id": "max",
                "value": 100
              },
              {
                "id": "custom.width",
                "value": 359
              }
            ]
          },
          {
            "matcher": {
              "id": "byName",
              "options": "Allocated GPU resources"
            },
            "properties": [
              {
                "id": "custom.cellOptions",
                "value": {
                  "type": "color-background"
                }
              },
              {
                "id": "color",
                "value": {
                  "mode": "continuous-GrYlRd"
                }
              },
              {
                "id": "custom.width",
                "value": 189
              }
            ]
          },
          {
            "matcher": {
              "id": "byName",
              "options": "Utilised GPU resources"
            },
            "properties": [
              {
                "id": "custom.cellOptions",
                "value": {
                  "type": "color-background"
                }
              },
              {
                "id": "color",
                "value": {
                  "mode": "continuous-RdYlGr"
                }
              },
              {
                "id": "custom.width",
                "value": 169
              }
            ]
          },
          {
            "matcher": {
              "id": "byName",
              "options": "Total GPU resources"
            },
            "properties": [
              {
                "id": "custom.width",
                "value": 155
              }
            ]
          }
        ]
      },
      "gridPos": {
        "h": 6,
        "w": 24,
        "x": 0,
        "y": 20
      },
      "id": 85,
      "options": {
        "cellHeight": "sm",
        "showHeader": true,
        "sortBy": [
          {
            "desc": true,
            "displayName": "GPU Card Status"
          }
        ]
      },
      "pluginVersion": "12.4.3",
      "targets": [
        {
          "datasource": {
            "type": "prometheus",
            "uid": "prometheus"
          },
          "editorMode": "code",
          "exemplar": false,
          "expr": "count(DCGM_FI_DEV_GPU_UTIL{Hostname=~\"$hostname\"}) by (Hostname)",
          "format": "table",
          "instant": true,
          "legendFormat": "__auto",
          "range": false,
          "refId": "A"
        },
        {
          "datasource": {
            "type": "prometheus",
            "uid": "prometheus"
          },
          "editorMode": "code",
          "exemplar": false,
          "expr": "avg by (Hostname,modelName,host_ip,DCGM_FI_DRIVER_VERSION) (DCGM_FI_DEV_GPU_UTIL{Hostname=~\"$hostname\"} * on (pod) group_left (host_ip) kube_pod_info)",
          "format": "table",
          "instant": true,
          "legendFormat": "__auto",
          "range": false,
          "refId": "B"
        },
        {
          "datasource": {
            "type": "prometheus",
            "uid": "prometheus"
          },
          "editorMode": "code",
          "exemplar": false,
          "expr": "label_replace(kube_node_info{node=~\"$hostname\"},\"Hostname\",\"$1\",\"node\",\"(.*)\")",
          "format": "table",
          "instant": true,
          "legendFormat": "__auto",
          "range": false,
          "refId": "C"
        },
        {
          "datasource": {
            "type": "prometheus",
            "uid": "prometheus"
          },
          "editorMode": "code",
          "exemplar": false,
          "expr": "label_replace(sum by (node) (irate(container_cpu_usage_seconds_total{container!=\"\",node=~\"$hostname\"}[2m]))  / sum by (node) (kube_node_status_allocatable{resource=\"cpu\", unit=\"core\", node=~\"$hostname\"}),\"Hostname\",\"$1\",\"node\",\"(.*)\")",
          "format": "table",
          "instant": true,
          "legendFormat": "CPU Utilization",
          "range": false,
          "refId": "D"
        },
        {
          "datasource": {
            "type": "prometheus",
            "uid": "prometheus"
          },
          "editorMode": "code",
          "exemplar": false,
          "expr": "label_replace(sum by (node) (container_memory_working_set_bytes{container!=\"\",node=~\"$hostname\"}) / sum by (node) (kube_node_status_allocatable{resource=\"memory\", unit=\"byte\", node=~\"$hostname\"}),\"Hostname\",\"$1\",\"node\",\"(.*)\")",
          "format": "table",
          "instant": true,
          "legendFormat": "Memory Usage",
          "range": false,
          "refId": "E"
        },
        {
          "datasource": {
            "type": "prometheus",
            "uid": "prometheus"
          },
          "editorMode": "code",
          "exemplar": false,
          "expr": "avg by (nodename, host_ip) (\n  label_replace(\n    node_hwmon_temp_celsius\n      * on(instance) group_left(nodename)\n      node_uname_info{nodename=~\"$hostname\"},\n    \"host_ip\", \"$1\", \"instance\", \"([^:]+):.*\"\n  )\n)",
          "format": "table",
          "instant": true,
          "legendFormat": "Memory Clock Frequency",
          "range": false,
          "refId": "F"
        },
        {
          "datasource": {
            "type": "prometheus",
            "uid": "prometheus"
          },
          "editorMode": "code",
          "exemplar": false,
          "expr": "count(DCGM_FI_DEV_GPU_UTIL{Hostname=~\"$hostname\"} * on (pod) group_left(host_ip) kube_pod_info) by (Hostname,host_ip)",
          "format": "table",
          "instant": true,
          "legendFormat": "__auto",
          "range": false,
          "refId": "G"
        },
        {
          "datasource": {
            "type": "prometheus",
            "uid": "prometheus"
          },
          "editorMode": "code",
          "exemplar": false,
          "expr": "count(\n  DCGM_FI_DEV_GPU_UTIL{Hostname=~\"$hostname\"} \n  * on (pod) group_left(exported_pod) \n  kube_pod_info{pod!=\"\"}\n) by (Hostname)",
          "format": "table",
          "instant": true,
          "legendFormat": "__auto",
          "range": false,
          "refId": "H"
        },
        {
          "datasource": {
            "type": "prometheus",
            "uid": "prometheus"
          },
          "editorMode": "code",
          "exemplar": false,
          "expr": "sum by (Hostname) (avg_over_time(DCGM_FI_DEV_GPU_UTIL{Hostname=~\"$hostname\"}[1m]) > bool 0)",
          "format": "table",
          "instant": true,
          "legendFormat": "__auto",
          "range": false,
          "refId": "I"
        }
      ],
      "title": "GPU Compute Card Host Status & Version Information Overview",
      "transformations": [
        {
          "id": "merge",
          "options": {}
        },
        {
          "id": "filterFieldsByName",
          "options": {
            "include": {
              "names": [
                "Hostname",
                "host_ip",
                "kernel_version",
                "os_image",
                "Value #D",
                "Value #E",
                "Value #F",
                "Value #G",
                "Value #H",
                "Value #I"
              ]
            }
          }
        },
        {
          "id": "organize",
          "options": {
            "excludeByName": {},
            "includeByName": {},
            "indexByName": {
              "Hostname": 0,
              "Value #D": 4,
              "Value #E": 5,
              "Value #F": 6,
              "host_ip": 1,
              "kernel_version": 2,
              "os_image": 3
            },
            "renameByName": {
              "DCGM_FI_DRIVER_VERSION": "NVIDIA Driver Version",
              "Hostname": "Hostname",
              "Value #A": "GPU Card Status",
              "Value #D": "CPU Utilization",
              "Value #E": "Memory Usage",
              "Value #F": "Host Temperature",
              "Value #G": "Total GPU resources",
              "Value #H": "Allocated GPU resources",
              "Value #I": "Utilised GPU resources",
              "host_ip": "Host IP",
              "kernel_version": "Kernel",
              "modelName": "Chip Type",
              "os_image": "Operating System Version",
              "release": "Kernel"
            }
          }
        }
      ],
      "type": "table"
    },
    {
      "datasource": {
        "type": "prometheus",
        "uid": "prometheus"
      },
      "fieldConfig": {
        "defaults": {
          "color": {
            "mode": "palette-classic"
          },
          "custom": {
            "axisBorderShow": false,
            "axisCenteredZero": false,
            "axisColorMode": "text",
            "axisLabel": "",
            "axisPlacement": "auto",
            "barAlignment": 0,
            "barWidthFactor": 0.6,
            "drawStyle": "line",
            "fillOpacity": 0,
            "gradientMode": "none",
            "hideFrom": {
              "legend": false,
              "tooltip": false,
              "viz": false
            },
            "insertNulls": false,
            "lineInterpolation": "linear",
            "lineWidth": 1,
            "pointSize": 5,
            "scaleDistribution": {
              "type": "linear"
            },
            "showPoints": "auto",
            "showValues": false,
            "spanNulls": false,
            "stacking": {
              "group": "A",
              "mode": "none"
            },
            "thresholdsStyle": {
              "mode": "off"
            }
          },
          "mappings": [],
          "thresholds": {
            "mode": "absolute",
            "steps": [
              {
                "color": "green",
                "value": 0
              },
              {
                "color": "red",
                "value": 80
              }
            ]
          },
          "unit": "watt"
        },
        "overrides": []
      },
      "gridPos": {
        "h": 8,
        "w": 24,
        "x": 0,
        "y": 26
      },
      "id": 86,
      "options": {
        "legend": {
          "calcs": [
            "mean",
            "lastNotNull",
            "min",
            "max"
          ],
          "displayMode": "table",
          "placement": "right",
          "showLegend": true
        },
        "tooltip": {
          "hideZeros": false,
          "mode": "single",
          "sort": "none"
        }
      },
      "pluginVersion": "12.4.3",
      "targets": [
        {
          "datasource": {
            "type": "prometheus",
            "uid": "prometheus"
          },
          "editorMode": "code",
          "expr": "avg by (Hostname,host_ip, gpu, modelName, UUID) (DCGM_FI_DEV_POWER_USAGE{Hostname=~\"$hostname\"})",
          "instant": false,
          "legendFormat": "{{Hostname}} - GPU {{gpu}} - {{ modelName }}",
          "range": true,
          "refId": "A"
        }
      ],
      "title": "GPU Power Usage",
      "type": "timeseries"
    },
    {
      "datasource": {
        "type": "prometheus",
        "uid": "${idc}"
      },
      "fieldConfig": {
        "defaults": {
          "color": {
            "mode": "palette-classic"
          },
          "custom": {
            "axisBorderShow": false,
            "axisCenteredZero": false,
            "axisColorMode": "text",
            "axisLabel": "",
            "axisPlacement": "auto",
            "fillOpacity": 80,
            "gradientMode": "hue",
            "hideFrom": {
              "legend": false,
              "tooltip": false,
              "viz": false
            },
            "lineWidth": 1,
            "scaleDistribution": {
              "type": "linear"
            },
            "thresholdsStyle": {
              "mode": "off"
            }
          },
          "mappings": [],
          "thresholds": {
            "mode": "absolute",
            "steps": [
              {
                "color": "green",
                "value": 0
              },
              {
                "color": "red",
                "value": 80
              }
            ]
          },
          "unit": "percent"
        },
        "overrides": []
      },
      "gridPos": {
        "h": 8,
        "w": 24,
        "x": 0,
        "y": 34
      },
      "id": 77,
      "interval": "$interval",
      "options": {
        "barRadius": 0,
        "barWidth": 0.97,
        "fullHighlight": false,
        "groupWidth": 0.7,
        "legend": {
          "calcs": [
            "lastNotNull",
            "max"
          ],
          "displayMode": "table",
          "placement": "right",
          "showLegend": true,
          "sortBy": "Last *",
          "sortDesc": true
        },
        "orientation": "auto",
        "showValue": "always",
        "stacking": "none",
        "tooltip": {
          "hideZeros": false,
          "mode": "single",
          "sort": "asc"
        },
        "xTickLabelRotation": 0,
        "xTickLabelSpacing": 0
      },
      "pluginVersion": "12.4.3",
      "targets": [
        {
          "datasource": {
            "type": "prometheus",
            "uid": "${idc}"
          },
          "editorMode": "code",
          "expr": "sum by (Hostname,host_ip) (DCGM_FI_DEV_GPU_UTIL{Hostname=~\"$hostname\"} ) ",
          "instant": false,
          "legendFormat": "{{host_ip}}",
          "range": true,
          "refId": "A"
        }
      ],
      "title": "GPU Utilization",
      "type": "barchart"
    },
    {
      "datasource": {
        "type": "prometheus",
        "uid": "${idc}"
      },
      "description": "Individual and multi-device aggregate display",
      "fieldConfig": {
        "defaults": {
          "color": {
            "fixedColor": "blue",
            "mode": "fixed"
          },
          "custom": {
            "axisBorderShow": false,
            "axisCenteredZero": false,
            "axisColorMode": "text",
            "axisLabel": "",
            "axisPlacement": "auto",
            "barAlignment": 0,
            "barWidthFactor": 0.6,
            "drawStyle": "line",
            "fillOpacity": 40,
            "gradientMode": "hue",
            "hideFrom": {
              "legend": false,
              "tooltip": false,
              "viz": false
            },
            "insertNulls": false,
            "lineInterpolation": "linear",
            "lineWidth": 1,
            "pointSize": 5,
            "scaleDistribution": {
              "type": "linear"
            },
            "showPoints": "always",
            "showValues": false,
            "spanNulls": false,
            "stacking": {
              "group": "A",
              "mode": "none"
            },
            "thresholdsStyle": {
              "mode": "off"
            }
          },
          "fieldMinMax": false,
          "mappings": [],
          "thresholds": {
            "mode": "absolute",
            "steps": [
              {
                "color": "green",
                "value": 0
              },
              {
                "color": "red",
                "value": 80
              }
            ]
          },
          "unit": "percent"
        },
        "overrides": [
          {
            "matcher": {
              "id": "byName",
              "options": "GPU Utilization"
            },
            "properties": [
              {
                "id": "color",
                "value": {
                  "fixedColor": "orange",
                  "mode": "fixed"
                }
              }
            ]
          }
        ]
      },
      "gridPos": {
        "h": 11,
        "w": 12,
        "x": 0,
        "y": 42
      },
      "id": 48,
      "options": {
        "legend": {
          "calcs": [
            "max",
            "last"
          ],
          "displayMode": "list",
          "placement": "bottom",
          "showLegend": true
        },
        "tooltip": {
          "hideZeros": false,
          "mode": "single",
          "sort": "none"
        }
      },
      "pluginVersion": "12.4.3",
      "targets": [
        {
          "datasource": {
            "type": "prometheus",
            "uid": "${idc}"
          },
          "editorMode": "code",
          "exemplar": false,
          "expr": "avg(DCGM_FI_DEV_GPU_UTIL{Hostname=~\"$hostname\"})",
          "format": "time_series",
          "instant": false,
          "legendFormat": "GPU Utilization",
          "range": true,
          "refId": "A"
        }
      ],
      "title": "GPU Total Utilization Trend",
      "type": "timeseries"
    },
    {
      "datasource": {
        "type": "prometheus",
        "uid": "${idc}"
      },
      "fieldConfig": {
        "defaults": {
          "color": {
            "mode": "thresholds"
          },
          "custom": {
            "align": "center",
            "cellOptions": {
              "type": "auto"
            },
            "footer": {
              "reducers": []
            },
            "inspect": false
          },
          "mappings": [],
          "thresholds": {
            "mode": "absolute",
            "steps": [
              {
                "color": "green",
                "value": 0
              },
              {
                "color": "red",
                "value": 80
              }
            ]
          }
        },
        "overrides": [
          {
            "matcher": {
              "id": "byName",
              "options": "Pod"
            },
            "properties": [
              {
                "id": "custom.cellOptions",
                "value": {
                  "type": "color-background"
                }
              }
            ]
          },
          {
            "matcher": {
              "id": "byName",
              "options": "NameSpace"
            },
            "properties": [
              {
                "id": "custom.cellOptions",
                "value": {
                  "type": "color-background"
                }
              },
              {
                "id": "color",
                "value": {
                  "fixedColor": "blue",
                  "mode": "fixed"
                }
              }
            ]
          },
          {
            "matcher": {
              "id": "byName",
              "options": "Hostname"
            },
            "properties": [
              {
                "id": "custom.cellOptions",
                "value": {
                  "type": "color-text"
                }
              },
              {
                "id": "color",
                "value": {
                  "fixedColor": "blue",
                  "mode": "fixed"
                }
              }
            ]
          },
          {
            "matcher": {
              "id": "byName",
              "options": "Host IP"
            },
            "properties": [
              {
                "id": "custom.cellOptions",
                "value": {
                  "type": "color-text"
                }
              },
              {
                "id": "color",
                "value": {
                  "fixedColor": "blue",
                  "mode": "fixed"
                }
              }
            ]
          },
          {
            "matcher": {
              "id": "byName",
              "options": "GPU Card Index"
            },
            "properties": [
              {
                "id": "custom.cellOptions",
                "value": {
                  "type": "color-text"
                }
              },
              {
                "id": "color",
                "value": {
                  "fixedColor": "blue",
                  "mode": "fixed"
                }
              }
            ]
          },
          {
            "matcher": {
              "id": "byName",
              "options": "GPU Memory Utilization"
            },
            "properties": [
              {
                "id": "unit",
                "value": "percentunit"
              },
              {
                "id": "decimals",
                "value": 1
              },
              {
                "id": "custom.cellOptions",
                "value": {
                  "mode": "lcd",
                  "type": "gauge"
                }
              },
              {
                "id": "color",
                "value": {
                  "mode": "continuous-GrYlRd"
                }
              },
              {
                "id": "min",
                "value": 0
              },
              {
                "id": "max",
                "value": 1
              }
            ]
          },
          {
            "matcher": {
              "id": "byName",
              "options": "GPU Utilization"
            },
            "properties": [
              {
                "id": "unit",
                "value": "percent"
              },
              {
                "id": "decimals"
              },
              {
                "id": "custom.cellOptions",
                "value": {
                  "mode": "lcd",
                  "type": "gauge"
                }
              },
              {
                "id": "color",
                "value": {
                  "mode": "continuous-GrYlRd"
                }
              }
            ]
          }
        ]
      },
      "gridPos": {
        "h": 11,
        "w": 12,
        "x": 12,
        "y": 42
      },
      "id": 66,
      "options": {
        "cellHeight": "sm",
        "showHeader": true,
        "sortBy": []
      },
      "pluginVersion": "12.4.3",
      "targets": [
        {
          "datasource": {
            "type": "prometheus",
            "uid": "${idc}"
          },
          "editorMode": "code",
          "exemplar": false,
          "expr": "sum by (Hostname, namespace, pod) (\n  DCGM_FI_DEV_GPU_UTIL{Hostname=~\"$hostname\"} \n  * on (pod) group_left(namespace) \n  kube_pod_info{namespace=~\"$namespace\"}\n)",
          "format": "table",
          "instant": true,
          "legendFormat": "__auto",
          "range": false,
          "refId": "A"
        },
        {
          "datasource": {
            "type": "prometheus",
            "uid": "${idc}"
          },
          "editorMode": "code",
          "exemplar": false,
          "expr": "(\n  sum by (Hostname, namespace) (\n    DCGM_FI_DEV_FB_USED{Hostname=~\"$hostname\"} \n    * on (pod) group_left(namespace) \n    kube_pod_info{namespace=~\"$namespace\"}\n  )\n  / \n  sum by (Hostname, namespace) (\n    (DCGM_FI_DEV_FB_USED{Hostname=~\"$hostname\"} + DCGM_FI_DEV_FB_FREE{Hostname=~\"$hostname\"}) \n    * on (pod) group_left(namespace) \n    kube_pod_info{namespace=~\"$namespace\"}\n  )\n) * 100",
          "format": "table",
          "instant": true,
          "legendFormat": "__auto",
          "range": false,
          "refId": "B"
        }
      ],
      "title": "GPU Resource Utilization Details (Pod-level Granularity)",
      "transformations": [
        {
          "id": "merge",
          "options": {}
        },
        {
          "id": "organize",
          "options": {
            "excludeByName": {},
            "includeByName": {},
            "indexByName": {
              "DCGM_FI_DRIVER_VERSION": 1,
              "Hostname": 2,
              "Time": 0,
              "UUID": 4,
              "Value #A": 19,
              "Value #B": 18,
              "container": 5,
              "device": 6,
              "endpoint": 7,
              "exported_container": 8,
              "exported_namespace": 9,
              "exported_pod": 10,
              "gpu": 11,
              "host_ip": 3,
              "instance": 12,
              "job": 13,
              "modelName": 14,
              "namespace": 15,
              "pod": 16,
              "service": 17
            },
            "renameByName": {
              "Hostname": "Hostname",
              "Value #A": "GPU Utilization",
              "Value #B": "GPU Memory Utilization",
              "exported_namespace": "NameSpace",
              "exported_pod": "Pod",
              "gpu": "GPU Card Index",
              "host_ip": "Host IP"
            }
          }
        },
        {
          "id": "filterFieldsByName",
          "options": {
            "include": {
              "names": [
                "Hostname",
                "Host IP",
                "NameSpace",
                "Pod",
                "GPU Card Index",
                "GPU Memory Utilization",
                "GPU Utilization"
              ]
            }
          }
        }
      ],
      "type": "table"
    },
    {
      "datasource": {
        "type": "prometheus",
        "uid": "${idc}"
      },
      "fieldConfig": {
        "defaults": {
          "color": {
            "mode": "palette-classic"
          },
          "decimals": 2,
          "mappings": [],
          "max": 100,
          "min": 0,
          "thresholds": {
            "mode": "absolute",
            "steps": [
              {
                "color": "green",
                "value": 0
              },
              {
                "color": "red",
                "value": 80
              }
            ]
          },
          "unit": "percent"
        },
        "overrides": []
      },
      "gridPos": {
        "h": 8,
        "w": 12,
        "x": 0,
        "y": 53
      },
      "id": 78,
      "options": {
        "displayMode": "lcd",
        "legend": {
          "calcs": [],
          "displayMode": "list",
          "placement": "bottom",
          "showLegend": false
        },
        "maxVizHeight": 300,
        "minVizHeight": 16,
        "minVizWidth": 8,
        "namePlacement": "auto",
        "orientation": "auto",
        "reduceOptions": {
          "calcs": [
            "lastNotNull"
          ],
          "fields": "",
          "values": false
        },
        "showUnfilled": true,
        "sizing": "auto",
        "valueMode": "color"
      },
      "pluginVersion": "12.4.3",
      "targets": [
        {
          "datasource": {
            "type": "prometheus",
            "uid": "P1809F7CD0C75ACF3"
          },
          "editorMode": "code",
          "expr": "avg by (Hostname,host_ip) (DCGM_FI_DEV_GPU_UTIL{Hostname=~\"$hostname\"} * on (pod) group_left (host_ip) kube_pod_info) ",
          "instant": false,
          "legendFormat": "{{host_ip}}",
          "range": true,
          "refId": "A"
        }
      ],
      "title": "GPU Utilization (Single Node)",
      "type": "bargauge"
    },
    {
      "datasource": {
        "type": "prometheus",
        "uid": "${idc}"
      },
      "fieldConfig": {
        "defaults": {
          "color": {
            "mode": "thresholds"
          },
          "decimals": 2,
          "mappings": [],
          "max": 100,
          "min": 0,
          "thresholds": {
            "mode": "absolute",
            "steps": [
              {
                "color": "green",
                "value": 0
              },
              {
                "color": "#EAB839",
                "value": 50
              },
              {
                "color": "#EF843C",
                "value": 60
              },
              {
                "color": "red",
                "value": 80
              }
            ]
          },
          "unit": "percent"
        },
        "overrides": []
      },
      "gridPos": {
        "h": 8,
        "w": 12,
        "x": 12,
        "y": 53
      },
      "id": 79,
      "options": {
        "displayMode": "gradient",
        "legend": {
          "calcs": [],
          "displayMode": "list",
          "placement": "bottom",
          "showLegend": false
        },
        "maxVizHeight": 300,
        "minVizHeight": 16,
        "minVizWidth": 8,
        "namePlacement": "auto",
        "orientation": "auto",
        "reduceOptions": {
          "calcs": [
            "mean"
          ],
          "fields": "",
          "values": false
        },
        "showUnfilled": true,
        "sizing": "auto",
        "valueMode": "color"
      },
      "pluginVersion": "12.4.3",
      "targets": [
        {
          "datasource": {
            "type": "prometheus",
            "uid": "${idc}"
          },
          "editorMode": "code",
          "expr": "(sum(DCGM_FI_DEV_FB_USED{pod!=\"\",Hostname=~\"$hostname\"} * on (pod) group_left (host_ip) kube_pod_info) by (Hostname,host_ip))/(sum(DCGM_FI_DEV_FB_USED{Hostname=~\"$hostname\"} * on (pod) group_left (host_ip) kube_pod_info) by (Hostname,host_ip)+sum(DCGM_FI_DEV_FB_FREE{Hostname=~\"$hostname\"} * on (pod) group_left (host_ip) kube_pod_info) by (Hostname,host_ip)) * 100",
          "instant": false,
          "legendFormat": "{{host_ip}}",
          "range": true,
          "refId": "A"
        }
      ],
      "title": "GPU Memory Utilization (Single Node)",
      "type": "bargauge"
    }
  ],
  "preload": false,
  "refresh": "10s",
  "schemaVersion": 42,
  "tags": [
    "A100",
    "A800",
    "H100",
    "Intelligent Computing Center",
    "NVIDIA",
    "GPU",
    "kason"
  ],
  "templating": {
    "list": [
      {
        "current": {
          "text": "Prometheus",
          "value": "prometheus"
        },
        "includeAll": false,
        "name": "idc",
        "options": [],
        "query": "prometheus",
        "refresh": 1,
        "regex": "",
        "type": "datasource"
      },
      {
        "current": {
          "text": "All",
          "value": [
            "$__all"
          ]
        },
        "datasource": {
          "type": "prometheus",
          "uid": "${idc}"
        },
        "definition": "label_values(DCGM_FI_DEV_DEC_UTIL,Hostname)",
        "includeAll": true,
        "label": "Hostname",
        "multi": true,
        "name": "hostname",
        "options": [],
        "query": {
          "qryType": 1,
          "query": "label_values(DCGM_FI_DEV_DEC_UTIL,Hostname)",
          "refId": "PrometheusVariableQueryEditor-VariableQuery"
        },
        "refresh": 1,
        "regex": "",
        "regexApplyTo": "value",
        "sort": 1,
        "type": "query"
      },
      {
        "auto": false,
        "auto_count": 30,
        "auto_min": "10s",
        "current": {
          "text": "1h",
          "value": "1h"
        },
        "label": "Interval Time",
        "name": "interval",
        "options": [
          {
            "selected": false,
            "text": "1m",
            "value": "1m"
          },
          {
            "selected": false,
            "text": "10m",
            "value": "10m"
          },
          {
            "selected": false,
            "text": "30m",
            "value": "30m"
          },
          {
            "selected": true,
            "text": "1h",
            "value": "1h"
          },
          {
            "selected": false,
            "text": "6h",
            "value": "6h"
          },
          {
            "selected": false,
            "text": "12h",
            "value": "12h"
          },
          {
            "selected": false,
            "text": "1d",
            "value": "1d"
          },
          {
            "selected": false,
            "text": "2d",
            "value": "2d"
          },
          {
            "selected": false,
            "text": "7d",
            "value": "7d"
          },
          {
            "selected": false,
            "text": "14d",
            "value": "14d"
          },
          {
            "selected": false,
            "text": "30d",
            "value": "30d"
          }
        ],
        "query": "1m,10m,30m,1h,6h,12h,1d,2d,7d,14d,30d",
        "refresh": 2,
        "type": "interval"
      },
      {
        "allValue": ".*",
        "current": {
          "text": "All",
          "value": "$__all"
        },
        "datasource": {
          "type": "prometheus",
          "uid": "${idc}"
        },
        "definition": "label_values(DCGM_FI_DEV_GPU_UTIL,exported_namespace)",
        "includeAll": true,
        "multi": true,
        "name": "namespace",
        "options": [],
        "query": {
          "qryType": 1,
          "query": "label_values(DCGM_FI_DEV_GPU_UTIL,exported_namespace)",
          "refId": "PrometheusVariableQueryEditor-VariableQuery"
        },
        "refresh": 1,
        "regex": "",
        "regexApplyTo": "value",
        "type": "query"
      }
    ]
  },
  "time": {
    "from": "now-1h",
    "to": "now"
  },
  "timepicker": {
    "refresh_intervals": [
      "10s",
      "30s",
      "1m",
      "5m",
      "15m",
      "30m",
      "1h",
      "2h"
    ]
  },
  "timezone": "browser",
  "title": "AI Intelligent Computing - GPU Resource Monitoring Overview",
  "uid": "gpu-resource-monitoring-overview",
  "version": 7,
  "weekStart": ""
}